lightcli.py
setup.cfg
setup.py
lightcli.egg-info/PKG-INFO
lightcli.egg-info/SOURCES.txt
lightcli.egg-info/dependency_links.txt
lightcli.egg-info/top_level.txt