Metadata-Version: 1.1
Name: lightcli
Version: 1.1
Summary: A lightweight terminal interaction library for Python
Home-page: https://github.com/dogoncouch/lightcli
Author: Dan Persons
Author-email: dpersonsdev@gmail.com
License: UNKNOWN
Keywords: python-library,python3-library,input,input-method,python-module,python3-module,cli,cli-utilities,input-validation
Platform: UNKNOWN
Classifier: Development Status :: 5 - Production/Stable
Classifier: Environment :: Other Environment
Classifier: Intended Audience :: Developers
Classifier: License :: OSI Approved :: MIT License
Classifier: Natural Language :: English
Classifier: Operating System :: POSIX
Classifier: Programming Language :: Python :: 3
Classifier: Topic :: Software Development :: Libraries :: Python Modules
